{"config_name": "neat_grid_0days",
 "logging_level": 0,
 "long": {"auto_unstuck_ema_dist": 0.0019082438961395415,
          "auto_unstuck_wallet_exposure_threshold": 0.026830030062635957,
          "backwards_tp": true,
          "ema_span_0": 502.0428690410733,
          "ema_span_1": 108.94361205469475,
          "enabled": true,
          "eprice_exp_base": 1.0473832493322606,
          "eqty_exp_base": 1.990077200091741,
          "grid_span": 0.19879596007548558,
          "initial_eprice_ema_dist": -0.0653700921569559,
          "initial_qty_pct": 0.011089234076288658,
          "markup_range": 0.001900862926579134,
          "max_n_entry_orders": 8,
          "min_markup": 0.006142691899280402,
          "n_close_orders": 4,
          "wallet_exposure_limit": 1},
 "short": {"auto_unstuck_ema_dist": 0.0011286922472785604,
           "auto_unstuck_wallet_exposure_threshold": 0.03924595230714203,
           "backwards_tp": true,
           "ema_span_0": 13.801986832421244,
           "ema_span_1": 243.42213199011417,
           "enabled": true,
           "eprice_exp_base": 1.0005419205772363,
           "eqty_exp_base": 2.0685167779479605,
           "grid_span": 0.3575190152424474,
           "initial_eprice_ema_dist": 0.001183248411828647,
           "initial_qty_pct": 0.010194635580520079,
           "markup_range": 0.006880899984257438,
           "max_n_entry_orders": 18,
           "min_markup": 0.0034089557038270283,
           "n_close_orders": 4,
           "wallet_exposure_limit": 1}}