{"config_name": "neat_grid_0days",
 "logging_level": 0,
 "long": {"auto_unstuck_ema_dist": 0.0008375319742205117,
          "auto_unstuck_wallet_exposure_threshold": 0.030745690481397473,
          "backwards_tp": true,
          "ema_span_0": 1231.3327168919564,
          "ema_span_1": 244.7450793066676,
          "enabled": true,
          "eprice_exp_base": 1.0001592838692526,
          "eqty_exp_base": 1.104750670194,
          "grid_span": 0.34255107435405585,
          "initial_eprice_ema_dist": 0.002472919893039929,
          "initial_qty_pct": 0.011194100924642483,
          "markup_range": 0.00439538781959691,
          "max_n_entry_orders": 8,
          "min_markup": 0.003741272258183316,
          "n_close_orders": 12,
          "wallet_exposure_limit": 1},
 "short": {"auto_unstuck_ema_dist": 0.0028260549444773953,
           "auto_unstuck_wallet_exposure_threshold": 0.03725770445285247,
           "backwards_tp": true,
           "ema_span_0": 953.3582569947656,
           "ema_span_1": 127.04987775212385,
           "enabled": true,
           "eprice_exp_base": 1.1305353974298453,
           "eqty_exp_base": 1.790615277830647,
           "grid_span": 0.16208479400592496,
           "initial_eprice_ema_dist": -0.0012497277437510275,
           "initial_qty_pct": 0.011941483176270825,
           "markup_range": 0.006244460857117984,
           "max_n_entry_orders": 10,
           "min_markup": 0.0048988562298664775,
           "n_close_orders": 15,
           "wallet_exposure_limit": 1}}