{"config_name": "clock_0days",
 "long": {"backwards_tp": true,
          "delay_between_fills_minutes_close": 590.5633691917151,
          "delay_between_fills_minutes_entry": 1381.4169659621261,
          "delay_weight_close": 0.0,
          "delay_weight_entry": 12.394413844731522,
          "ema_dist_close": -0.00768415922951044,
          "ema_dist_entry": 0.0015996851255744152,
          "ema_span_0": 647.203976826022,
          "ema_span_1": 256.5055895230371,
          "enabled": true,
          "markup_range": 0.033536189120824775,
          "min_markup": 0.0052787946448329005,
          "n_close_orders": 4,
          "qty_pct_close": 0.01012923877920174,
          "qty_pct_entry": 0.011340718978618844,
          "wallet_exposure_limit": 1.0,
          "we_multiplier_close": 0.0,
          "we_multiplier_entry": 84.45255539080003},
 "short": {"backwards_tp": true,
           "delay_between_fills_minutes_close": 1102.5382813434503,
           "delay_between_fills_minutes_entry": 509.3803554365753,
           "delay_weight_close": 0.0,
           "delay_weight_entry": 8.253641707055818,
           "ema_dist_close": 0.0004991436421471464,
           "ema_dist_entry": 0.0029437859237263124,
           "ema_span_0": 1231.1316704442322,
           "ema_span_1": 1360.6596403991327,
           "enabled": true,
           "markup_range": 0.005333667842585371,
           "min_markup": 0.0045943481835009755,
           "n_close_orders": 12,
           "qty_pct_close": 0.013842667492120264,
           "qty_pct_entry": 0.017314314648869285,
           "wallet_exposure_limit": 1.0,
           "we_multiplier_close": 0.0,
           "we_multiplier_entry": 145.53980570898193}}