{"config_name": "recursive_grid_0days",
 "logging_level": 0,
 "long": {"auto_unstuck_ema_dist": 0.002601700060261469,
          "auto_unstuck_wallet_exposure_threshold": 0.032509324676618115,
          "backwards_tp": true,
          "ddown_factor": 0.15572875676464792,
          "ema_span_0": 70.75996248512197,
          "ema_span_1": 23.91241370477809,
          "enabled": true,
          "initial_eprice_ema_dist": 0.004,
          "initial_qty_pct": 0.01013058160597158,
          "markup_range": 0.00017965908207479874,
          "min_markup": 0.002360185662105618,
          "n_close_orders": 11,
          "rentry_pprice_dist": 0.00904732184901534,
          "rentry_pprice_dist_wallet_exposure_weighting": 0.8371479219320042,
          "wallet_exposure_limit": 1.0},
 "short": {"auto_unstuck_ema_dist": 0.001285821081827295,
           "auto_unstuck_wallet_exposure_threshold": 0.040046424076117346,
           "backwards_tp": true,
           "ddown_factor": 1.5577915980755666,
           "ema_span_0": 999.7047405995305,
           "ema_span_1": 357.1896150576582,
           "enabled": true,
           "initial_eprice_ema_dist": -0.010743564169045993,
           "initial_qty_pct": 0.01148116168951163,
           "markup_range": 0.0013080609244183166,
           "min_markup": 0.003199240995036451,
           "n_close_orders": 14,
           "rentry_pprice_dist": 0.025166703612064797,
           "rentry_pprice_dist_wallet_exposure_weighting": 2.5872130117358685,
           "wallet_exposure_limit": 1.0}}