{"config_name": "recursive_grid_0days",
 "logging_level": 0,
 "long": {"auto_unstuck_ema_dist": 0.0029472383819563516,
          "auto_unstuck_wallet_exposure_threshold": 0.047784773106313204,
          "backwards_tp": true,
          "ddown_factor": 0.1000003406806138,
          "ema_span_0": 473.3975885731676,
          "ema_span_1": 1067.7665923250786,
          "enabled": true,
          "initial_eprice_ema_dist": 0.0029882955675168623,
          "initial_qty_pct": 0.017306625474256116,
          "markup_range": 0.005059955882202116,
          "min_markup": 0.005492804418842325,
          "n_close_orders": 5,
          "rentry_pprice_dist": 0.041711779449499914,
          "rentry_pprice_dist_wallet_exposure_weighting": 1.782176844711261,
          "wallet_exposure_limit": 1},
 "short": {"auto_unstuck_ema_dist": 0.0023743008876258836,
           "auto_unstuck_wallet_exposure_threshold": 0.030977118469734666,
           "backwards_tp": true,
           "ddown_factor": 0.10013312914828808,
           "ema_span_0": 1227.523475557377,
           "ema_span_1": 364.77295205327044,
           "enabled": true,
           "initial_eprice_ema_dist": 0.00393791808947494,
           "initial_qty_pct": 0.012081500681307292,
           "markup_range": 0.0067766035276407115,
           "min_markup": 0.0025963395712418837,
           "n_close_orders": 5,
           "rentry_pprice_dist": 0.03720477149053689,
           "rentry_pprice_dist_wallet_exposure_weighting": 6.413736360274096,
           "wallet_exposure_limit": 1}}