{"config_name": "clock_0days",
 "long": {"backwards_tp": true,
          "delay_between_fills_minutes_close": 611.8472174321304,
          "delay_between_fills_minutes_entry": 1348.351310543866,
          "delay_weight_close": 0.0005722780129249379,
          "delay_weight_entry": 12.553167226858651,
          "ema_dist_close": 0.003923468465022305,
          "ema_dist_entry": -0.003670725419199173,
          "ema_span_0": 685.2404370977532,
          "ema_span_1": 1141.6904684922195,
          "enabled": true,
          "markup_range": 0.014112218700855479,
          "min_markup": 0.007213700953470872,
          "n_close_orders": 6,
          "qty_pct_close": 0.010074401086728696,
          "qty_pct_entry": 0.010033982813977944,
          "wallet_exposure_limit": 1,
          "we_multiplier_close": 0,
          "we_multiplier_entry": 54.51300768823448},
 "short": {"backwards_tp": true,
           "delay_between_fills_minutes_close": 1413.7126410936091,
           "delay_between_fills_minutes_entry": 771.288247323637,
           "delay_weight_close": 9.974790514756808,
           "delay_weight_entry": 5.103836140198686,
           "ema_dist_close": 0.001704187674792159,
           "ema_dist_entry": -0.011634464237561192,
           "ema_span_0": 1316.2887307584404,
           "ema_span_1": 397.8085751189282,
           "enabled": true,
           "markup_range": 0.020202394554187472,
           "min_markup": 0.008109957723629553,
           "n_close_orders": 5,
           "qty_pct_close": 0.013539557219822813,
           "qty_pct_entry": 0.01,
           "wallet_exposure_limit": 1,
           "we_multiplier_close": 0,
           "we_multiplier_entry": 35.824051015534984}}