{"config_name": "clock_0days",
 "long": {"backwards_tp": true,
          "delay_between_fills_minutes_close": 760.2322159358207,
          "delay_between_fills_minutes_entry": 1349.4768739550047,
          "delay_weight_close": 0.0,
          "delay_weight_entry": 11.376300174369826,
          "ema_dist_close": 0.0019419135075398701,
          "ema_dist_entry": -0.006147219830510711,
          "ema_span_0": 1038.096871415764,
          "ema_span_1": 549.4253303472583,
          "enabled": true,
          "markup_range": 0.03145423865812336,
          "min_markup": 0.0020327666679458905,
          "n_close_orders": 8,
          "qty_pct_close": 0.010007303180078852,
          "qty_pct_entry": 0.011335934241699519,
          "wallet_exposure_limit": 1.0,
          "we_multiplier_close": 0.0,
          "we_multiplier_entry": 44.06705331612959},
 "short": {"backwards_tp": true,
           "delay_between_fills_minutes_close": 679.9775089103408,
           "delay_between_fills_minutes_entry": 592.9335189582442,
           "delay_weight_close": 0.0,
           "delay_weight_entry": 26.641804810306205,
           "ema_dist_close": -9.455810379530461e-05,
           "ema_dist_entry": 0.0033768164983594045,
           "ema_span_0": 713.1410438286524,
           "ema_span_1": 1057.9581001967845,
           "enabled": true,
           "markup_range": 0.002124419955663829,
           "min_markup": 0.009999354231967116,
           "n_close_orders": 4,
           "qty_pct_close": 0.02699447792789941,
           "qty_pct_entry": 0.010056608190643499,
           "wallet_exposure_limit": 1.0,
           "we_multiplier_close": 0.0,
           "we_multiplier_entry": 55.04737222057234}}