{"config_name": "clock_0days",
 "long": {"backwards_tp": true,
          "delay_between_fills_minutes_close": 1187.5159125172547,
          "delay_between_fills_minutes_entry": 934.8549918166714,
          "delay_weight_close": 183.14955251118843,
          "delay_weight_entry": 7.4020982801189765,
          "ema_dist_close": 0.003,
          "ema_dist_entry": -0.0007201214543245009,
          "ema_span_0": 5.001084731280378,
          "ema_span_1": 1187.9062419776928,
          "enabled": true,
          "markup_range": 0.03590588705800657,
          "min_markup": 0.009547482339989087,
          "n_close_orders": 13,
          "qty_pct_close": 0.03359142586996403,
          "qty_pct_entry": 0.010024028951959725,
          "wallet_exposure_limit": 1,
          "we_multiplier_close": 0,
          "we_multiplier_entry": 56.500187349590405},
 "short": {"backwards_tp": true,
           "delay_between_fills_minutes_close": 890.9132441901123,
           "delay_between_fills_minutes_entry": 1119.5761792952046,
           "delay_weight_close": 0.04715964129038191,
           "delay_weight_entry": 9.158190273877167,
           "ema_dist_close": -0.020863864126173134,
           "ema_dist_entry": -0.002873092458369048,
           "ema_span_0": 1096.809161915279,
           "ema_span_1": 802.5502356098751,
           "enabled": true,
           "markup_range": 0.032738775224799004,
           "min_markup": 0.0067307725542914395,
           "n_close_orders": 14,
           "qty_pct_close": 0.01087981826445631,
           "qty_pct_entry": 0.01207524522974419,
           "wallet_exposure_limit": 1,
           "we_multiplier_close": 0,
           "we_multiplier_entry": 128.38509729200064}}