{"config_name": "clock_0days",
 "long": {"backwards_tp": true,
          "delay_between_fills_minutes_close": 1223.2222401393096,
          "delay_between_fills_minutes_entry": 646.2444403329883,
          "delay_weight_close": 0.1287801964102248,
          "delay_weight_entry": 25.72650110105462,
          "ema_dist_close": -0.005799553989668527,
          "ema_dist_entry": 0.00021015635637898253,
          "ema_span_0": 1067.4717266073615,
          "ema_span_1": 815.1394209953332,
          "enabled": true,
          "markup_range": 0.0022629341171275775,
          "min_markup": 0.0046200628388333295,
          "n_close_orders": 6,
          "qty_pct_close": 0.03685275026162734,
          "qty_pct_entry": 0.011628076557322684,
          "wallet_exposure_limit": 1,
          "we_multiplier_close": 0,
          "we_multiplier_entry": 164.6094960709121},
 "short": {"backwards_tp": true,
           "delay_between_fills_minutes_close": 942.7140120056342,
           "delay_between_fills_minutes_entry": 1152.9789088762138,
           "delay_weight_close": 0,
           "delay_weight_entry": 5.596846800576707,
           "ema_dist_close": -0.020064680883941137,
           "ema_dist_entry": 0.0014531106527657953,
           "ema_span_0": 700.3191808924661,
           "ema_span_1": 1256.108367944059,
           "enabled": true,
           "markup_range": 0.029403538540038136,
           "min_markup": 0.009022363942650982,
           "n_close_orders": 7,
           "qty_pct_close": 0.011411958809870296,
           "qty_pct_entry": 0.011356672070102993,
           "wallet_exposure_limit": 1,
           "we_multiplier_close": 0,
           "we_multiplier_entry": 96.5287923271223}}