{"config_name": "clock_0days",
 "long": {"backwards_tp": true,
          "delay_between_fills_minutes_close": 810.466946887245,
          "delay_between_fills_minutes_entry": 975.036032988387,
          "delay_weight_close": 0,
          "delay_weight_entry": 9.230378594177795,
          "ema_dist_close": -0.004723901218558702,
          "ema_dist_entry": 0.0029970953306604473,
          "ema_span_0": 1303.5154718029069,
          "ema_span_1": 1161.2450776606752,
          "enabled": true,
          "markup_range": 0.030332542219882276,
          "min_markup": 0.00952799629034398,
          "n_close_orders": 8,
          "qty_pct_close": 0.01000664846186205,
          "qty_pct_entry": 0.01031640885206189,
          "wallet_exposure_limit": 1,
          "we_multiplier_close": 0,
          "we_multiplier_entry": 51.29848349064663},
 "short": {"backwards_tp": true,
           "delay_between_fills_minutes_close": 890.9132441901123,
           "delay_between_fills_minutes_entry": 1119.5761792952046,
           "delay_weight_close": 0.04715964129038191,
           "delay_weight_entry": 9.158190273877167,
           "ema_dist_close": -0.020863864126173134,
           "ema_dist_entry": -0.002873092458369048,
           "ema_span_0": 1096.809161915279,
           "ema_span_1": 802.5502356098751,
           "enabled": true,
           "markup_range": 0.032738775224799004,
           "min_markup": 0.0067307725542914395,
           "n_close_orders": 14,
           "qty_pct_close": 0.01087981826445631,
           "qty_pct_entry": 0.01207524522974419,
           "wallet_exposure_limit": 1,
           "we_multiplier_close": 0,
           "we_multiplier_entry": 128.38509729200064}}