{"config_name": "clock_0days",
 "long": {"backwards_tp": true,
          "delay_between_fills_minutes_close": 50.23864177530594,
          "delay_between_fills_minutes_entry": 302.9479100672574,
          "delay_weight_close": 7.482066621509332,
          "delay_weight_entry": 17.440238072940033,
          "ema_dist_close": -0.005457531282720727,
          "ema_dist_entry": 0.01173754595102604,
          "ema_span_0": 145.9821116071048,
          "ema_span_1": 423.62863741214676,
          "enabled": true,
          "markup_range": 0.1,
          "min_markup": 0.1,
          "n_close_orders": 5,
          "qty_pct_close": 0.23362223343783164,
          "qty_pct_entry": 0.022854756570704862,
          "wallet_exposure_limit": 1.0,
          "we_multiplier_close": 1.8545499671403307,
          "we_multiplier_entry": 54.271520776306154},
 "short": {"backwards_tp": true,
           "delay_between_fills_minutes_close": 28.691361290546116,
           "delay_between_fills_minutes_entry": 1015.1061033341498,
           "delay_weight_close": 19.721987011457223,
           "delay_weight_entry": 10.462096414261087,
           "ema_dist_close": 0.01532631099789195,
           "ema_dist_entry": -0.003960792308397854,
           "ema_span_0": 126.06550887237107,
           "ema_span_1": 849.0400858205313,
           "enabled": true,
           "markup_range": 0.07970978675775597,
           "min_markup": 0.09530028682424997,
           "n_close_orders": 15,
           "qty_pct_close": 0.3295573907863614,
           "qty_pct_entry": 0.01,
           "wallet_exposure_limit": 1.0,
           "we_multiplier_close": 0.3688858063189864,
           "we_multiplier_entry": 58.63013754506841}}