{"config_name": "longonly_binance_etcusdt_214days_adg0.063%_bkr100.00%_eqbal95.26%",
 "logging_level": 0,
 "long": {"enabled": true,
          "eprice_exp_base": 1.618034,
          "eprice_pprice_diff": 0.007041996028426638,
          "grid_span": 0.08439029899058342,
          "initial_qty_pct": 0.003195512439206384,
          "markup_range": 0.008856073690058641,
          "max_n_entry_orders": 10,
          "min_markup": 0.002417871027991234,
          "n_close_orders": 7,
          "pbr_limit": 0.15,
          "secondary_grid_spacing": 0.3119770067294098,
          "secondary_pbr_allocation": 0.5},
 "shrt": {"enabled": false,
          "eprice_exp_base": 1.618034,
          "eprice_pprice_diff": 0.001,
          "grid_span": 0.03,
          "initial_qty_pct": 0.001,
          "markup_range": 0.004,
          "max_n_entry_orders": 10,
          "min_markup": 0.0005,
          "n_close_orders": 7,
          "pbr_limit": 0.5,
          "secondary_grid_spacing": 0.21,
          "secondary_pbr_allocation": 0}}