{"config_name": "scalp_longonly_binance_ltcusdt_213days_adg0.21%_bkr100.00%",
 "logging_level": 0,
 "long": {"enabled": true,
          "markup_range": 0.009219680247709812,
          "min_markup": 0.005489752563451053,
          "n_close_orders": 9,
          "primary_ddown_factor": 2.888335660054352,
          "primary_grid_spacing": 0.02668943263384615,
          "primary_grid_spacing_pbr_weighting": [0.0069644875858164345,
                                                 0.04673419824488185],
          "primary_initial_qty_pct": 0.00273824165435276,
          "primary_pbr_limit": 0.3333,
          "secondary_ddown_factor": 0.4956758770531294,
          "secondary_grid_spacing": 0.10292494103067411,
          "secondary_pbr_limit_added": 0.3333},
 "shrt": {"enabled": false,
          "markup_range": 0.004,
          "min_markup": 0.0005,
          "n_close_orders": 10,
          "primary_ddown_factor": 0.3,
          "primary_grid_spacing": 0.001,
          "primary_grid_spacing_pbr_weighting": [0, 0],
          "primary_initial_qty_pct": 0.001,
          "primary_pbr_limit": 0.3,
          "secondary_ddown_factor": 0.3,
          "secondary_grid_spacing": 0.09,
          "secondary_pbr_limit_added": 0.3}}