{"config_name": "neat_grid_0days",
 "logging_level": 0,
 "long": {"auto_unstuck_ema_dist": 0.0026071693369002545,
          "auto_unstuck_wallet_exposure_threshold": 0.06397089766159697,
          "backwards_tp": true,
          "ema_span_0": 1174.7857230218262,
          "ema_span_1": 1146.6170583828418,
          "enabled": true,
          "eprice_exp_base": 1.1462309902541632,
          "eqty_exp_base": 2.1324170006177354,
          "grid_span": 0.26683438970230244,
          "initial_eprice_ema_dist": -0.022217903252685755,
          "initial_qty_pct": 0.01781085813386806,
          "markup_range": 0.0037627403991689744,
          "max_n_entry_orders": 6,
          "min_markup": 0.0038159039109234697,
          "n_close_orders": 14,
          "wallet_exposure_limit": 1.0},
 "short": {"auto_unstuck_ema_dist": -0.00681936736378239,
           "auto_unstuck_wallet_exposure_threshold": 0.04356045913222897,
           "backwards_tp": true,
           "ema_span_0": 820.409286435148,
           "ema_span_1": 1440.0,
           "enabled": true,
           "eprice_exp_base": 1.0716023501939214,
           "eqty_exp_base": 1.5390513243857462,
           "grid_span": 0.32557138552743237,
           "initial_eprice_ema_dist": -0.013008122323197608,
           "initial_qty_pct": 0.01389160541133769,
           "markup_range": 0.021485526153850923,
           "max_n_entry_orders": 13,
           "min_markup": 0.009776721743383593,
           "n_close_orders": 1,
           "wallet_exposure_limit": 1.0}}