{"config_name": "clock_0days",
 "long": {"backwards_tp": true,
          "delay_between_fills_minutes_close": 1372.3714105823267,
          "delay_between_fills_minutes_entry": 1394.8347618659923,
          "delay_weight_close": 0.0,
          "delay_weight_entry": 11.552907188871735,
          "ema_dist_close": -0.0016757628838846121,
          "ema_dist_entry": 0.0029201028992715027,
          "ema_span_0": 1176.5983782184496,
          "ema_span_1": 1266.6498397048354,
          "enabled": true,
          "markup_range": 0.02637531083172806,
          "min_markup": 0.008880031475194776,
          "n_close_orders": 12,
          "qty_pct_close": 0.012203303516040922,
          "qty_pct_entry": 0.01354940317908622,
          "wallet_exposure_limit": 1.0,
          "we_multiplier_close": 0.0,
          "we_multiplier_entry": 18.50399566602955},
 "short": {"backwards_tp": true,
           "delay_between_fills_minutes_close": 1184.5107930797194,
           "delay_between_fills_minutes_entry": 475.2002011602138,
           "delay_weight_close": 0.0,
           "delay_weight_entry": 20.063445927737177,
           "ema_dist_close": -0.0021991003303444097,
           "ema_dist_entry": -0.005068117408007421,
           "ema_span_0": 1411.5595383621214,
           "ema_span_1": 256.84174237383326,
           "enabled": true,
           "markup_range": 0.012247167587446069,
           "min_markup": 0.007269880764530288,
           "n_close_orders": 12,
           "qty_pct_close": 0.03061486884152728,
           "qty_pct_entry": 0.011779582196272556,
           "wallet_exposure_limit": 1.0,
           "we_multiplier_close": 0.0,
           "we_multiplier_entry": 22.478779959824728}}