{"config_name": "clock_0days",
 "long": {"backwards_tp": true,
          "delay_between_fills_minutes_close": 713.4794618397858,
          "delay_between_fills_minutes_entry": 991.2118576718657,
          "delay_weight_close": 0.0,
          "delay_weight_entry": 15.39408961905036,
          "ema_dist_close": 0.0029874790517238617,
          "ema_dist_entry": 0.002992240553617329,
          "ema_span_0": 1434.666239684808,
          "ema_span_1": 1379.2492332703848,
          "enabled": true,
          "markup_range": 0.025073716385322554,
          "min_markup": 0.007155840871522752,
          "n_close_orders": 15,
          "qty_pct_close": 0.0329903191180085,
          "qty_pct_entry": 0.01,
          "wallet_exposure_limit": 1.0,
          "we_multiplier_close": 0.0,
          "we_multiplier_entry": 69.9430298124366},
 "short": {"backwards_tp": true,
           "delay_between_fills_minutes_close": 1319.824440645874,
           "delay_between_fills_minutes_entry": 915.9735032921251,
           "delay_weight_close": 0.0,
           "delay_weight_entry": 7.483846384312691,
           "ema_dist_close": 0.002473455755457076,
           "ema_dist_entry": 0.000972489459682991,
           "ema_span_0": 1436.6658764650094,
           "ema_span_1": 1377.1290779533888,
           "enabled": true,
           "markup_range": 0.016841644526360142,
           "min_markup": 0.008209333970485223,
           "n_close_orders": 2,
           "qty_pct_close": 0.017809669305847955,
           "qty_pct_entry": 0.010000331837764782,
           "wallet_exposure_limit": 1.0,
           "we_multiplier_close": 0.0,
           "we_multiplier_entry": 44.279393699015834}}