{"config_name": "recursive_grid_0days",
 "logging_level": 0,
 "long": {"auto_unstuck_ema_dist": 0.0010844287763653643,
          "auto_unstuck_wallet_exposure_threshold": 0.030969291001158937,
          "backwards_tp": true,
          "ddown_factor": 2.601784654887675,
          "ema_span_0": 539.976976753874,
          "ema_span_1": 266.4446070488581,
          "enabled": true,
          "initial_eprice_ema_dist": 0.014125705213471533,
          "initial_qty_pct": 0.0141619903320701,
          "markup_range": 0.009363598837583666,
          "min_markup": 0.0032935345725369257,
          "n_close_orders": 5,
          "rentry_pprice_dist": 0.03437311035142891,
          "rentry_pprice_dist_wallet_exposure_weighting": 3.62919345484811,
          "wallet_exposure_limit": 1.0},
 "short": {"auto_unstuck_ema_dist": 0.07417800827243161,
           "auto_unstuck_wallet_exposure_threshold": 0.07810075223982511,
           "backwards_tp": true,
           "ddown_factor": 2.5542698252761977,
           "ema_span_0": 687.3817248115614,
           "ema_span_1": 943.3201656870292,
           "enabled": true,
           "initial_eprice_ema_dist": 0.00739238888220113,
           "initial_qty_pct": 0.01342934530257428,
           "markup_range": 0.005268716934371232,
           "min_markup": 0.009614861083171021,
           "n_close_orders": 4,
           "rentry_pprice_dist": 0.041104184490418146,
           "rentry_pprice_dist_wallet_exposure_weighting": 9.08533819265784,
           "wallet_exposure_limit": 1.0}}